MANIFEST.in
README.rst
setup.cfg
setup.py
pyt/__init__.py
pyt/__main__.py
pyt/alias_helper.py
pyt/analysis_base.py
pyt/argument_helpers.py
pyt/ast_helper.py
pyt/base_cfg.py
pyt/constraint_table.py
pyt/definition_chains.py
pyt/draw.py
pyt/fixed_point.py
pyt/framework_adaptor.py
pyt/framework_helper.py
pyt/github_search.py
pyt/interprocedural_cfg.py
pyt/intraprocedural_cfg.py
pyt/label_visitor.py
pyt/lattice.py
pyt/liveness.py
pyt/module_definitions.py
pyt/project_handler.py
pyt/reaching_definitions.py
pyt/reaching_definitions_base.py
pyt/reaching_definitions_taint.py
pyt/repo_runner.py
pyt/right_hand_side_visitor.py
pyt/save.py
pyt/trigger_definitions_parser.py
pyt/vars_visitor.py
pyt/vulnerabilities.py
pyt/vulnerability_log.py
pyt/trigger_definitions/django_trigger_words.pyt
pyt/trigger_definitions/flask_trigger_words.pyt
pyt/trigger_definitions/test_triggers.pyt
taint_analysis.egg-info/PKG-INFO
taint_analysis.egg-info/SOURCES.txt
taint_analysis.egg-info/dependency_links.txt
taint_analysis.egg-info/entry_points.txt
taint_analysis.egg-info/requires.txt
taint_analysis.egg-info/top_level.txt